kamera_alerk/NN.py
kamera_alerk/__init__.py
kamera_alerk/camera_hadler.py
kamera_alerk/db_handler.py
kamera_alerk/main.py
kamera_alerk/parsing.py
kamera_alerk/settings_handler.py
kamera_alerk/telegram_bot.py
kamera_alerk-0.2.0.dist-info/LICENSE
kamera_alerk-0.2.0.dist-info/METADATA
kamera_alerk-0.2.0.dist-info/WHEEL
kamera_alerk-0.2.0.dist-info/entry_points.txt
kamera_alerk-0.2.0.dist-info/top_level.txt
kamera_alerk-0.2.0.dist-info/RECORD
